incuna_mail.py
incuna_mail-4.1.1.dist-info/LICENSE
incuna_mail-4.1.1.dist-info/METADATA
incuna_mail-4.1.1.dist-info/WHEEL
incuna_mail-4.1.1.dist-info/top_level.txt
incuna_mail-4.1.1.dist-info/RECORD
